gitdata/__init__.py
gitdata/__main__.py
gitdata/__version__.py
gitdata/database.py
gitdata/digester.py
gitdata/graph.py
gitdata/graph2.py
gitdata/repositories.py
gitdata/repositories2.py
gitdata/solutions.py
gitdata/utils.py
gitdata/cli/__init__.py
gitdata/cli/cli.py
gitdata/cli/cli_remote.py
gitdata/sql/create_repository_sqlite3.sql
gitdata/sql/create_respository_sqlite3.sql
gitdata_cli-0.2.0.dist-info/METADATA
gitdata_cli-0.2.0.dist-info/WHEEL
gitdata_cli-0.2.0.dist-info/entry_points.txt
gitdata_cli-0.2.0.dist-info/top_level.txt
gitdata_cli-0.2.0.dist-info/RECORD
